odoo/addons/project_sale_order_link/README.rst
odoo/addons/project_sale_order_link/__init__.py
odoo/addons/project_sale_order_link/__manifest__.py
odoo/addons/project_sale_order_link/i18n/es.po
odoo/addons/project_sale_order_link/i18n/it.po
odoo/addons/project_sale_order_link/i18n/project_sale_order_link.pot
odoo/addons/project_sale_order_link/models/__init__.py
odoo/addons/project_sale_order_link/models/project.py
odoo/addons/project_sale_order_link/readme/CONTEXT.rst
odoo/addons/project_sale_order_link/readme/CONTRIBUTORS.rst
odoo/addons/project_sale_order_link/readme/DESCRIPTION.rst
odoo/addons/project_sale_order_link/readme/USAGE.rst
odoo/addons/project_sale_order_link/static/description/icon.png
odoo/addons/project_sale_order_link/static/description/index.html
odoo/addons/project_sale_order_link/tests/__init__.py
odoo/addons/project_sale_order_link/tests/test_project_sale_order_link.py
odoo/addons/project_sale_order_link/views/project_views.xml
odoo_addon_project_sale_order_link-15.0.1.0.1.4.dist-info/METADATA
odoo_addon_project_sale_order_link-15.0.1.0.1.4.dist-info/WHEEL
odoo_addon_project_sale_order_link-15.0.1.0.1.4.dist-info/top_level.txt
odoo_addon_project_sale_order_link-15.0.1.0.1.4.dist-info/RECORD
